memory_bank/__init__.py
memory_bank/memory_bank.py
memory_bank-0.1.2.dist-info/LICENSE
memory_bank-0.1.2.dist-info/METADATA
memory_bank-0.1.2.dist-info/WHEEL
memory_bank-0.1.2.dist-info/top_level.txt
memory_bank-0.1.2.dist-info/RECORD
