Metadata-Version: 2.1
Name: memory_bank
Version: 0.1.2
Summary: A simple Python library for managing chat message history in langchain
Home-page: https://github.com/Kaladin4/memory_bank
Author: Francisco Garófalo Jerez
Author-email: dalinargarofalo@gmail.com
Classifier: Development Status :: 3 - Alpha
Classifier: Intended Audience :: Developers
Classifier: License :: OSI Approved :: MIT License
Classifier: Operating System :: OS Independent
Classifier: Programming Language :: Python :: 3
Classifier: Programming Language :: Python :: 3.7
Classifier: Programming Language :: Python :: 3.8
Classifier: Programming Language :: Python :: 3.9
Classifier: Programming Language :: Python :: 3.10
Classifier: Programming Language :: Python :: 3.11
Classifier: Programming Language :: Python :: 3.12
Requires-Python: >=3.7
License-File: LICENSE
Requires-Dist: langchain-core
Provides-Extra: dev
Requires-Dist: langchain-anthropic ; extra == 'dev'
Requires-Dist: python-dotenv ; extra == 'dev'
